{"id": "61f458bd", "clues": [{"word": "router", "rank": 10.0, "goodness": 0.3256633548072777, "bad_minimax": -0.19696577781520527, "frequency": 4493.0, "neutrals_minimax": -0.11524460482608567, "variance": 0.48933962476264475}, {"word": "gateway", "rank": 15.0, "goodness": 0.3075440862843453, "bad_minimax": -0.12981834920542482, "frequency": 5783.0, "neutrals_minimax": -0.12636451774647786, "variance": 0.37263596273356514}, {"word": "subsystem", "rank": 28.75, "goodness": 0.29638477140487657, "bad_minimax": -0.19670920154797222, "frequency": 12749.0, "neutrals_minimax": -0.12603224631651563, "variance": 0.4102258896092292}, {"word": "interface", "rank": 47.5, "goodness": 0.2919368968557453, "bad_minimax": -0.1959765520474668, "frequency": 1480.0, "neutrals_minimax": -0.08451026957301877, "variance": 0.3495076196276834}, {"word": "node", "rank": 48.75, "goodness": 0.2916852950350608, "bad_minimax": -0.1690575890789002, "frequency": 3823.0, "neutrals_minimax": -0.11597252504559692, "variance": 0.40019731027329647}], "process_config": {"AVG_DIST_MULT": 1.15, "RANK_MULT": 1.25, "PRIMARY_SORT_BY_COLUMNS": ["goodness", "bad_minimax", "frequency", "neutrals_minimax"], "PRIMARY_SORT_ASCENDING": [false, false, false, false], "SECONDARY_SORT_BY_COLUMNS": ["rank", "variance", "goodness"], "SECONDARY_SORT_ASCENDING": [true, false, false], "SIZE": 2000, "HIGH_SIZE": 2000, "LOW_SIZE": 200, "ASSASSIN_CUTOFF": 0.78, "DEEP": true}, "words": [{"id": "d4c12b55", "word": "port", "type": "friend", "is_top_friend": true}, {"id": "6ff24d3b", "word": "server", "type": "friend", "is_top_friend": true}, {"id": "efc57b72", "word": "head", "type": "friend", "is_top_friend": false}, {"id": "7c613f2c", "word": "bridge", "type": "friend", "is_top_friend": false}, {"id": "65ea6404", "word": "scale", "type": "friend", "is_top_friend": false}, {"id": "0a7df411", "word": "day", "type": "friend", "is_top_friend": false}, {"id": "332f035c", "word": "fire", "type": "friend", "is_top_friend": false}, {"id": "e30cbd93", "word": "square", "type": "friend", "is_top_friend": false}, {"id": "88582060", "word": "marble", "type": "foe", "is_top_friend": null}, {"id": "6be0a45d", "word": "pit", "type": "foe", "is_top_friend": null}, {"id": "c071abab", "word": "limousine", "type": "foe", "is_top_friend": null}, {"id": "c3713b97", "word": "death", "type": "foe", "is_top_friend": null}, {"id": "9bc0e65a", "word": "bug", "type": "foe", "is_top_friend": null}, {"id": "723498ae", "word": "palm", "type": "foe", "is_top_friend": null}, {"id": "c53716bf", "word": "shoe", "type": "foe", "is_top_friend": null}, {"id": "465c30ea", "word": "pistol", "type": "foe", "is_top_friend": null}, {"id": "10d30e93", "word": "lemon", "type": "foe", "is_top_friend": null}, {"id": "19c7d252", "word": "charge", "type": "neutral", "is_top_friend": null}, {"id": "a769f6f2", "word": "compound", "type": "neutral", "is_top_friend": null}, {"id": "7c5e84e2", "word": "shark", "type": "neutral", "is_top_friend": null}, {"id": "472a5600", "word": "giant", "type": "neutral", "is_top_friend": null}, {"id": "0b4a77a7", "word": "belt", "type": "neutral", "is_top_friend": null}, {"id": "b8df64d5", "word": "moon", "type": "neutral", "is_top_friend": null}, {"id": "acf1e00d", "word": "fair", "type": "neutral", "is_top_friend": null}, {"id": "9c9273ff", "word": "yard", "type": "assassin", "is_top_friend": null}]}