{"id": "7683dccc", "clues": [{"word": "observatory", "rank": 2.5, "goodness": 0.32922524751113164, "bad_minimax": -0.34281482627373316, "frequency": 15617.0, "neutrals_minimax": -0.168905351437839, "variance": 0.6792248589368031}, {"word": "humpback", "rank": 3.75, "goodness": 0.30931051002756393, "bad_minimax": -0.2670605018577756, "frequency": 21762.0, "neutrals_minimax": -0.19372311165371411, "variance": 0.6331537402793482}, {"word": "whaling", "rank": 15.0, "goodness": 0.2839330272662757, "bad_minimax": -0.18556121981991347, "frequency": 16320.0, "neutrals_minimax": -0.18773256264024996, "variance": 0.5360774026467515}, {"word": "astronomer", "rank": 30.0, "goodness": 0.265690676451178, "bad_minimax": -0.35331155030729705, "frequency": 15890.0, "neutrals_minimax": -0.14443305007248128, "variance": 0.5595098042431217}, {"word": "dolphin", "rank": 32.5, "goodness": 0.2627620196260294, "bad_minimax": -0.4274392489249679, "frequency": 10258.0, "neutrals_minimax": -0.30103887639495935, "variance": 0.6746357436260056}], "process_config": {"AVG_DIST_MULT": 1.15, "RANK_MULT": 1.25, "PRIMARY_SORT_BY_COLUMNS": ["goodness", "bad_minimax", "frequency", "neutrals_minimax"], "PRIMARY_SORT_ASCENDING": [false, false, false, false], "SECONDARY_SORT_BY_COLUMNS": ["rank", "variance", "goodness"], "SECONDARY_SORT_ASCENDING": [true, false, false], "SIZE": 2000, "HIGH_SIZE": 2000, "LOW_SIZE": 200, "ASSASSIN_CUTOFF": 0.78, "DEEP": true}, "words": [{"id": "b495df29", "word": "whale", "type": "friend", "is_top_friend": true}, {"id": "887e7818", "word": "telescope", "type": "friend", "is_top_friend": true}, {"id": "1a4814bc", "word": "ambulance", "type": "friend", "is_top_friend": false}, {"id": "ca7fa331", "word": "bomb", "type": "friend", "is_top_friend": false}, {"id": "9269a19b", "word": "chest", "type": "friend", "is_top_friend": false}, {"id": "ba21d898", "word": "cast", "type": "friend", "is_top_friend": false}, {"id": "791476d7", "word": "knight", "type": "friend", "is_top_friend": false}, {"id": "01d9fdd4", "word": "jam", "type": "friend", "is_top_friend": false}, {"id": "4da9ead7", "word": "nail", "type": "foe", "is_top_friend": null}, {"id": "307132e4", "word": "fork", "type": "foe", "is_top_friend": null}, {"id": "28a05e47", "word": "horn", "type": "foe", "is_top_friend": null}, {"id": "becee877", "word": "berry", "type": "foe", "is_top_friend": null}, {"id": "37e6659e", "word": "triangle", "type": "foe", "is_top_friend": null}, {"id": "f40cd176", "word": "octopus", "type": "foe", "is_top_friend": null}, {"id": "cff623f0", "word": "pie", "type": "foe", "is_top_friend": null}, {"id": "7c614463", "word": "light", "type": "foe", "is_top_friend": null}, {"id": "c91932b7", "word": "moon", "type": "foe", "is_top_friend": null}, {"id": "42bcb658", "word": "ice", "type": "neutral", "is_top_friend": null}, {"id": "de67ea82", "word": "head", "type": "neutral", "is_top_friend": null}, {"id": "079cc293", "word": "pipe", "type": "neutral", "is_top_friend": null}, {"id": "7508a930", "word": "rabbit", "type": "neutral", "is_top_friend": null}, {"id": "91e61241", "word": "tick", "type": "neutral", "is_top_friend": null}, {"id": "5f8f5a5d", "word": "pan", "type": "neutral", "is_top_friend": null}, {"id": "b59ca11f", "word": "strike", "type": "neutral", "is_top_friend": null}, {"id": "fb397749", "word": "pitch", "type": "assassin", "is_top_friend": null}]}