{"id": "c4674acd", "clues": [{"word": "boardwalk", "rank": 8.75, "goodness": 0.25388570765373303, "bad_minimax": -0.1797166055592002, "frequency": 13506.0, "neutrals_minimax": -0.14175631150842036, "variance": 0.5173799244699712}, {"word": "pier", "rank": 8.75, "goodness": 0.2651200744476169, "bad_minimax": -0.1903029997954587, "frequency": 9278.0, "neutrals_minimax": -0.12239023806398497, "variance": 0.4846067454000451}, {"word": "patio", "rank": 18.75, "goodness": 0.24800106701852617, "bad_minimax": -0.35321426338254763, "frequency": 4068.0, "neutrals_minimax": -0.16534685942188823, "variance": 0.459656666584542}, {"word": "jetty", "rank": 23.75, "goodness": 0.2472232663514967, "bad_minimax": -0.21379771603883266, "frequency": 18082.0, "neutrals_minimax": -0.13362253269136218, "variance": 0.49563621146769427}, {"word": "lagoon", "rank": 26.25, "goodness": 0.2418553324622538, "bad_minimax": -0.17485569947550825, "frequency": 11301.0, "neutrals_minimax": -0.12810244328235829, "variance": 0.4737885453771307}], "process_config": {"AVG_DIST_MULT": 1.15, "RANK_MULT": 1.25, "PRIMARY_SORT_BY_COLUMNS": ["goodness", "bad_minimax", "frequency", "neutrals_minimax"], "PRIMARY_SORT_ASCENDING": [false, false, false, false], "SECONDARY_SORT_BY_COLUMNS": ["rank", "variance", "goodness"], "SECONDARY_SORT_ASCENDING": [true, false, false], "HIGH_SIZE": 2000, "LOW_SIZE": 200, "ASSASSIN_CUTOFF": 0.78}, "words": [{"id": "1ce04718", "word": "deck", "type": "friend", "is_top_friend": true}, {"id": "6099dbf0", "word": "pit", "type": "friend", "is_top_friend": true}, {"id": "b11a14fd", "word": "beach", "type": "friend", "is_top_friend": true}, {"id": "d0f85ca6", "word": "school", "type": "friend", "is_top_friend": false}, {"id": "9d8e3ee2", "word": "dice", "type": "friend", "is_top_friend": false}, {"id": "d5ad8fc6", "word": "pilot", "type": "friend", "is_top_friend": false}, {"id": "7a99887c", "word": "needle", "type": "friend", "is_top_friend": false}, {"id": "ea052a6b", "word": "heart", "type": "friend", "is_top_friend": false}, {"id": "22e68589", "word": "stock", "type": "foe", "is_top_friend": null}, {"id": "f6bb4ec3", "word": "bear", "type": "foe", "is_top_friend": null}, {"id": "6add7e20", "word": "wall", "type": "foe", "is_top_friend": null}, {"id": "15b162b1", "word": "cricket", "type": "foe", "is_top_friend": null}, {"id": "6242cc4a", "word": "satellite", "type": "foe", "is_top_friend": null}, {"id": "67d8797f", "word": "parachute", "type": "foe", "is_top_friend": null}, {"id": "7bbcc7c3", "word": "dance", "type": "foe", "is_top_friend": null}, {"id": "a9f523ff", "word": "gold", "type": "foe", "is_top_friend": null}, {"id": "4dc10a2b", "word": "play", "type": "foe", "is_top_friend": null}, {"id": "e9c4965c", "word": "doctor", "type": "neutral", "is_top_friend": null}, {"id": "9e87768c", "word": "shoe", "type": "neutral", "is_top_friend": null}, {"id": "01184ef2", "word": "field", "type": "neutral", "is_top_friend": null}, {"id": "0173fb3d", "word": "torch", "type": "neutral", "is_top_friend": null}, {"id": "62fca797", "word": "point", "type": "neutral", "is_top_friend": null}, {"id": "96dbc2c7", "word": "ring", "type": "neutral", "is_top_friend": null}, {"id": "6c621cb1", "word": "box", "type": "neutral", "is_top_friend": null}, {"id": "6ced5e41", "word": "pass", "type": "assassin", "is_top_friend": null}]}