{"id": "0bf00dc2", "clues": [{"word": "browser", "rank": 8.75, "goodness": 0.2758449541689519, "bad_minimax": -0.17800691561483362, "frequency": 1733.0, "neutrals_minimax": -0.469501643488702, "variance": 0.4524745345409813}, {"word": "subsystem", "rank": 47.5, "goodness": 0.25484656966525226, "bad_minimax": -0.2620694781731911, "frequency": 12749.0, "neutrals_minimax": -0.17480931764390786, "variance": 0.44023302518225477}, {"word": "daemon", "rank": 48.75, "goodness": 0.24609438293145117, "bad_minimax": -0.2601779700068835, "frequency": 13568.0, "neutrals_minimax": -0.23863153412659235, "variance": 0.5201532343331209}, {"word": "Zend", "rank": 50.0, "goodness": 0.24745609109169106, "bad_minimax": -0.1527954516022143, "frequency": 16227.0, "neutrals_minimax": -0.24790951605350312, "variance": 0.37815907534136767}, {"word": "executable", "rank": 91.25, "goodness": 0.23302767403022828, "bad_minimax": -0.249346660769491, "frequency": 9611.0, "neutrals_minimax": -0.3000574365205346, "variance": 0.451437412553007}], "process_config": {"AVG_DIST_MULT": 1.15, "RANK_MULT": 1.25, "PRIMARY_SORT_BY_COLUMNS": ["goodness", "bad_minimax", "frequency", "neutrals_minimax"], "PRIMARY_SORT_ASCENDING": [false, false, false, false], "SECONDARY_SORT_BY_COLUMNS": ["rank", "variance", "goodness"], "SECONDARY_SORT_ASCENDING": [true, false, false], "HIGH_SIZE": 2000, "LOW_SIZE": 200, "ASSASSIN_CUTOFF": 0.78}, "words": [{"id": "494de835", "word": "engine", "type": "friend", "is_top_friend": true}, {"id": "a90c91db", "word": "server", "type": "friend", "is_top_friend": true}, {"id": "e98a8e96", "word": "princess", "type": "friend", "is_top_friend": false}, {"id": "ce636d80", "word": "glass", "type": "friend", "is_top_friend": false}, {"id": "1c62c2eb", "word": "trip", "type": "friend", "is_top_friend": false}, {"id": "2ba243c3", "word": "hand", "type": "friend", "is_top_friend": false}, {"id": "b7c2eaf9", "word": "piano", "type": "friend", "is_top_friend": false}, {"id": "88b380e4", "word": "arm", "type": "friend", "is_top_friend": false}, {"id": "e4b803ea", "word": "battery", "type": "foe", "is_top_friend": null}, {"id": "ef0f96c0", "word": "diamond", "type": "foe", "is_top_friend": null}, {"id": "3b025669", "word": "time", "type": "foe", "is_top_friend": null}, {"id": "2a74a588", "word": "pistol", "type": "foe", "is_top_friend": null}, {"id": "1cbc9b3d", "word": "pyramid", "type": "foe", "is_top_friend": null}, {"id": "a4e06b16", "word": "block", "type": "foe", "is_top_friend": null}, {"id": "f87c54bc", "word": "mount", "type": "foe", "is_top_friend": null}, {"id": "709fc9da", "word": "root", "type": "foe", "is_top_friend": null}, {"id": "5f9490c5", "word": "iron", "type": "foe", "is_top_friend": null}, {"id": "49d76827", "word": "straw", "type": "neutral", "is_top_friend": null}, {"id": "a212087d", "word": "pan", "type": "neutral", "is_top_friend": null}, {"id": "3591394a", "word": "eye", "type": "neutral", "is_top_friend": null}, {"id": "a03ab499", "word": "fan", "type": "neutral", "is_top_friend": null}, {"id": "530cfb15", "word": "web", "type": "neutral", "is_top_friend": null}, {"id": "46e0b914", "word": "spring", "type": "neutral", "is_top_friend": null}, {"id": "32a8b590", "word": "court", "type": "neutral", "is_top_friend": null}, {"id": "04586fa5", "word": "wave", "type": "assassin", "is_top_friend": null}]}