{"id": "5266fec0", "clues": [{"word": "behemoth", "rank": 6.25, "goodness": 0.2956485271106308, "bad_minimax": -0.15652694379165544, "frequency": 17476.0, "neutrals_minimax": -0.27063223846391066, "variance": 0.6227660994492926}, {"word": "goliath", "rank": 8.75, "goodness": 0.29148692467029547, "bad_minimax": -0.13405864944439308, "frequency": 26321.0, "neutrals_minimax": -0.26659867424841244, "variance": 0.5043786094304031}, {"word": "gigantic", "rank": 18.75, "goodness": 0.2680928699648888, "bad_minimax": -0.17331677320625707, "frequency": 7673.0, "neutrals_minimax": -0.32614370249831975, "variance": 0.5913767740132218}, {"word": "snail", "rank": 25.0, "goodness": 0.2645295634687915, "bad_minimax": -0.11642134316244164, "frequency": 11551.0, "neutrals_minimax": -0.29470181439307847, "variance": 0.3721144836752539}, {"word": "parasite", "rank": 35.0, "goodness": 0.25959647049806645, "bad_minimax": -0.08312543285986333, "frequency": 11613.0, "neutrals_minimax": -0.1952969899604625, "variance": 0.44600147867510437}], "process_config": {"AVG_DIST_MULT": 1.15, "RANK_MULT": 1.25, "PRIMARY_SORT_BY_COLUMNS": ["goodness", "bad_minimax", "frequency", "neutrals_minimax"], "PRIMARY_SORT_ASCENDING": [false, false, false, false], "SECONDARY_SORT_BY_COLUMNS": ["rank", "variance", "goodness"], "SECONDARY_SORT_ASCENDING": [true, false, false], "SIZE": 2000, "HIGH_SIZE": 2000, "LOW_SIZE": 200, "ASSASSIN_CUTOFF": 0.78, "DEEP": true}, "words": [{"id": "9d5ee5d3", "word": "giant", "type": "friend", "is_top_friend": true}, {"id": "50c52946", "word": "worm", "type": "friend", "is_top_friend": true}, {"id": "0172e5e1", "word": "church", "type": "friend", "is_top_friend": false}, {"id": "b26dd9f7", "word": "needle", "type": "friend", "is_top_friend": false}, {"id": "7e1d8081", "word": "spring", "type": "friend", "is_top_friend": false}, {"id": "f36d88be", "word": "fighter", "type": "friend", "is_top_friend": false}, {"id": "3e46171f", "word": "pilot", "type": "friend", "is_top_friend": false}, {"id": "b6a6aa91", "word": "fly", "type": "friend", "is_top_friend": false}, {"id": "f3822650", "word": "angel", "type": "friend", "is_top_friend": false}, {"id": "23133406", "word": "cloak", "type": "foe", "is_top_friend": null}, {"id": "4f6a8f28", "word": "brush", "type": "foe", "is_top_friend": null}, {"id": "d0f53a26", "word": "row", "type": "foe", "is_top_friend": null}, {"id": "56cfae17", "word": "hand", "type": "foe", "is_top_friend": null}, {"id": "ef66ee69", "word": "head", "type": "foe", "is_top_friend": null}, {"id": "4b8a25cf", "word": "pole", "type": "foe", "is_top_friend": null}, {"id": "fa1ff71d", "word": "chest", "type": "foe", "is_top_friend": null}, {"id": "1ba0c6bc", "word": "tag", "type": "foe", "is_top_friend": null}, {"id": "c48e6fa1", "word": "car", "type": "neutral", "is_top_friend": null}, {"id": "108d2a3e", "word": "robin", "type": "neutral", "is_top_friend": null}, {"id": "eb5404ad", "word": "tail", "type": "neutral", "is_top_friend": null}, {"id": "39aedb0b", "word": "dwarf", "type": "neutral", "is_top_friend": null}, {"id": "0e05509e", "word": "buffalo", "type": "neutral", "is_top_friend": null}, {"id": "d30f40ae", "word": "gold", "type": "neutral", "is_top_friend": null}, {"id": "e78d65c7", "word": "tap", "type": "neutral", "is_top_friend": null}, {"id": "58d9610e", "word": "game", "type": "assassin", "is_top_friend": null}]}