{"id": "5336007a", "clue_id": "f6666e8c", "process_config": {"AVG_DIST_MULT": 1.2, "RANK_MULT": 1.5, "PRIMARY_SORT_BY_COLUMNS": ["goodness", "bad_minimax", "frequency", "neutrals_minimax"], "SECONDARY_SORT_BY_COLUMNS": ["rank", "variance", "goodness"], "HIGH_SIZE": 2000, "LOW_SIZE": 200, "ASSASSIN_CUTOFF": 0.78}, "words": [{"id": "c98a0287", "word": "game", "type": "friend", "is_top": true}, {"id": "f30386d8", "word": "force", "type": "friend", "is_top": true}, {"id": "60de3ee8", "word": "stick", "type": "friend", "is_top": false}, {"id": "beae1674", "word": "rose", "type": "friend", "is_top": false}, {"id": "52051b73", "word": "palm", "type": "friend", "is_top": false}, {"id": "69b31f69", "word": "note", "type": "friend", "is_top": false}, {"id": "c01f3c33", "word": "tube", "type": "friend", "is_top": false}, {"id": "69ac5047", "word": "spider", "type": "friend", "is_top": false}, {"id": "8bb4faa7", "word": "space", "type": "foe", "is_top": null}, {"id": "50170bf9", "word": "worm", "type": "foe", "is_top": null}, {"id": "0ff1492a", "word": "robin", "type": "foe", "is_top": null}, {"id": "ada28667", "word": "bow", "type": "foe", "is_top": null}, {"id": "e656ab11", "word": "board", "type": "foe", "is_top": null}, {"id": "6017c1ae", "word": "nut", "type": "foe", "is_top": null}, {"id": "acb78513", "word": "marble", "type": "foe", "is_top": null}, {"id": "b03b7639", "word": "millionaire", "type": "foe", "is_top": null}, {"id": "d947ee34", "word": "degree", "type": "foe", "is_top": null}, {"id": "55a49e54", "word": "school", "type": "neutral", "is_top": null}, {"id": "4ebc4cc4", "word": "boot", "type": "neutral", "is_top": null}, {"id": "317fb848", "word": "hook", "type": "neutral", "is_top": null}, {"id": "ff221468", "word": "dwarf", "type": "neutral", "is_top": null}, {"id": "39878c82", "word": "pipe", "type": "neutral", "is_top": null}, {"id": "4c48484e", "word": "angel", "type": "neutral", "is_top": null}, {"id": "152a1969", "word": "hawk", "type": "neutral", "is_top": null}, {"id": "1150105e", "word": "battery", "type": "assassin", "is_top": null}]}